pyhottop/__init__.py
pyhottop/mock.py
pyhottop/pyhottop.py
pyhottop/cli/__init__.py
pyhottop/cli/config.py
pyhottop-0.2.6.dist-info/DESCRIPTION.rst
pyhottop-0.2.6.dist-info/METADATA
pyhottop-0.2.6.dist-info/RECORD
pyhottop-0.2.6.dist-info/WHEEL
pyhottop-0.2.6.dist-info/entry_points.txt
pyhottop-0.2.6.dist-info/metadata.json
pyhottop-0.2.6.dist-info/top_level.txt
