Metadata-Version: 2.0
Name: pyhottop
Version: 0.2.6
Summary: Interface for interacting with Hottop KN-8828b-2k+ roasters
Home-page: https://github.com/splitkeycoffee/pyhottop
Author: Brandon Dixon
Author-email: brandon@splitkeycoffee.com
License: MIT
Download-URL: https://github.com/splitkeycoffee/pyhottop/archive/master.zip
Keywords: coffee,coffee roasting,hottop,coffee tech
Platform: UNKNOWN
Classifier: Development Status :: 4 - Beta
Classifier: Intended Audience :: Developers
Classifier: License :: OSI Approved :: MIT License
Classifier: Natural Language :: English
Classifier: Programming Language :: Python
Classifier: Topic :: Software Development :: Libraries
Requires-Dist: pyserial
